deepl/__init__.py
deepl/__main__.py
deepl/adapter.py
deepl/enums.py
deepl/errors.py
deepl/translator.py
deepl.py-1.0.3.dist-info/LICENSE
deepl.py-1.0.3.dist-info/METADATA
deepl.py-1.0.3.dist-info/WHEEL
deepl.py-1.0.3.dist-info/top_level.txt
deepl.py-1.0.3.dist-info/RECORD
