Metadata-Version: 2.1
Name: deepl.py
Version: 1.0.3
Summary: A Python wrapper for the DeepL API
Home-page: https://github.com/grarich123/deepl.py
Author: grarich
Author-email: grarich123@gmail.com
License: UNKNOWN
Platform: UNKNOWN
Classifier: Programming Language :: Python :: 3.8
Classifier: Programming Language :: Python :: 3.9
Classifier: License :: OSI Approved :: MIT License
Classifier: Operating System :: OS Independent
Requires-Dist: aiohttp
Requires-Dist: requests
